pylittle/__init__.py
pylittle/main.py
pylittle-0.0.2.dist-info/METADATA
pylittle-0.0.2.dist-info/WHEEL
pylittle-0.0.2.dist-info/entry_points.txt
pylittle-0.0.2.dist-info/top_level.txt
pylittle-0.0.2.dist-info/RECORD
