Metadata-Version: 2.1
Name: pylittle
Version: 0.0.2
Summary: pylittle test
Home-page: https://www.pylittle.io/
Author: pylittle Systems, Inc.
Author-email: support@pylittle.io
License: Proprietary License
Project-URL: Homepage, https://www.pylittle.io/
Project-URL: Documentation, https://www.pylittle.io/
Project-URL: Contact, https://www.pylittle.io/
Project-URL: End-User License Agreement, https://www.pylittle.io/
Keywords: pylittle
Classifier: Development Status :: 4 - Beta
Classifier: Environment :: Console
Classifier: Environment :: Other Environment
Classifier: Intended Audience :: Developers
Classifier: Intended Audience :: Information Technology
Classifier: Intended Audience :: Science/Research
Classifier: Intended Audience :: System Administrators
Classifier: License :: Other/Proprietary License
Classifier: Operating System :: OS Independent
Classifier: Programming Language :: Python :: 3.8
Classifier: Programming Language :: Python :: 3.9
Classifier: Programming Language :: Python :: 3.10
Classifier: Programming Language :: Python :: 3.11
Classifier: Topic :: Database
Classifier: Topic :: Software Development
Classifier: Topic :: Software Development :: Libraries
Classifier: Topic :: Software Development :: Libraries :: Application Frameworks
Classifier: Topic :: Software Development :: Libraries :: Python Modules
Requires-Python: >=3.8
Requires-Dist: requests (>=2.19.0)
Provides-Extra: grpc
Requires-Dist: protobuf (~=3.20.0) ; extra == 'grpc'
